{
  "job": [
    {
      "_children_": [
        {
          "_type_": "description",
          "_value_": "Crawl_WebRepo_e465f56c120a4af083959687"
        },
        {
          "_type_": "repository_connection",
          "_value_": "WebRepo_e465f56c120a4af083959687"
        },
        {
          "_type_": "document_specification",
          "_children_": [
            {
              "_type_": "seeds",
              "_value_": "https://www.francelabs.com"
            },
            {
              "_type_": "includes",
              "_value_": ".*"
            },
            {
              "_type_": "includesindex",
              "_value_": ".*"
            },
            {
              "_type_": "limittoseeds",
              "_value_": "",
              "_attribute_value": "true"
            },
            {
              "_type_": "excludes",
              "_value_": "(/[^\\/]+){7}/?.*\r\n.*\\.css.*\r\n.*\\.jpg.*\r\n.*\\.jpeg.*\r\n.*\\.bmp.*\r\n.*\\.gif.*\r\n.*\\.png.*\r\n.*\\.ico.*\r\n.*\\.svg.*\r\n.*\\.ico.*\r\n.*\\.js.*"
            },
            {
              "_type_": "excludesindex",
              "_value_": ""
            },
            {
              "_type_": "excludescontentindex",
              "_value_": ""
            }
          ]
        },
        {
          "_type_": "pipelinestage",
          "_children_": [
            {
              "_type_": "stage_id",
              "_value_": "0"
            },
            {
              "_type_": "stage_isoutput",
              "_value_": "false"
            },
            {
              "_type_": "stage_connectionname",
              "_value_": "EmptierFilter"
            },
            {
              "_type_": "stage_specification",
              "_children_": [
                {
                  "_type_": "includefilter",
                  "_value_": "",
                  "_attribute_regex": "\\.(?i)avi(?-i)$"
                },
                {
                  "_type_": "includefilter",
                  "_value_": "",
                  "_attribute_regex": "\\.(?i)mp4(?-i)$"
                },
                {
                  "_type_": "includefilter",
                  "_value_": "",
                  "_attribute_regex": "\\.(?i)mpeg(?-i)$"
                },
                {
                  "_type_": "includefilter",
                  "_value_": "",
                  "_attribute_regex": "\\.(?i)mkv(?-i)$"
                },
                {
                  "_type_": "includefilter",
                  "_value_": "",
                  "_attribute_regex": "\\.(?i)mov(?-i)$"
                },
                {
                  "_type_": "includefilter",
                  "_value_": "",
                  "_attribute_regex": "\\.(?i)wmv(?-i)$"
                },
                {
                  "_type_": "includefilter",
                  "_value_": "",
                  "_attribute_regex": "\\.(?i)flv(?-i)$"
                },
                {
                  "_type_": "includefilter",
                  "_value_": "",
                  "_attribute_regex": "\\.(?i)mp3(?-i)$"
                },
                {
                  "_type_": "includefilter",
                  "_value_": "",
                  "_attribute_regex": "\\.(?i)wav(?-i)$"
                },
                {
                  "_type_": "includefilter",
                  "_value_": "",
                  "_attribute_regex": "\\.(?i)wma(?-i)$"
                },
                {
                  "_type_": "includefilter",
                  "_value_": "",
                  "_attribute_regex": "\\.(?i)flac(?-i)$"
                },
                {
                  "_type_": "includefilter",
                  "_value_": "",
                  "_attribute_regex": "\\.(?i)aac(?-i)$"
                },
                {
                  "_type_": "includefilter",
                  "_value_": "",
                  "_attribute_regex": "\\.(?i)aiff(?-i)$"
                },
                {
                  "_type_": "includefilter",
                  "_value_": "",
                  "_attribute_regex": "\\.(?i)ogg(?-i)$"
                },
                {
                  "_type_": "maxdocsize",
                  "_value_": "",
                  "_attribute_value": "100000000"
                }
              ]
            }
          ]
        },
        
        
        {
          "_type_": "pipelinestage",
          "_children_": [
            {
              "_type_": "stage_id",
              "_value_": "1"
            },
            {
              "_type_": "stage_prerequisite",
              "_value_": "0"
            },
            {
              "_type_": "stage_isoutput",
              "_value_": "false"
            },
            {
              "_type_": "stage_connectionname",
              "_value_": "FilterConnector"
            },
            {
              "_type_": "stage_specification",
              "_children_": [
                {
                  "_type_": "mindate",
                  "_value_": "",
                  "_attribute_value": "0"
                },
                {
                  "_type_": "minlength",
                  "_value_": "",
                  "_attribute_value": "0"
                },
                {
                  "_type_": "maxlength",
                  "_value_": "",
                  "_attribute_value": "500000000"
                },
                {
                  "_type_": "mimetypes",
                  "_value_": "application/msword\r\napplication/vnd.ms-excel\r\napplication/vnd.openxmlformats-officedocument.wordprocessingml.document\r\napplication/vnd.openxmlformats-officedocument.spreadsheetml.sheet\r\ntext/html\r\napplication/pdf\r\napplication/vnd.ms-powerpoint\r\napplication/vnd.openxmlformats-officedocument.presentationml.presentation\r\napplication/vnd.oasis.opendocument.text\r\napplication/vnd.oasis.opendocument.spreadsheet\r\napplication/vnd.oasis.opendocument.formula\r\napplication/rtf\r\ntext/plain\r\ntext/html; charset=utf-8\r\ntext/html;charset=utf-8\r\ntext/plain; charset=utf-8\r\ntext/plain;charset=utf-8\r\ntext/xml\r\ntext/xml; charset=utf-8\r\ntext/xml;charset=utf-8"
                },
                {
                  "_type_": "extensions",
                  "_value_": "*\r\nlog\r\ndoc\r\ndocx\r\nxls\r\nxlsx\r\nppt\r\npptx\r\nhtml\r\npdf\r\nodt\r\nods\r\nrtf\r\ntxt\r\nmp3\r\nmp4\r\nwav\r\nogg\r\nflac\r\ntorrent"
                }
              ]
            }
          ]
        },
        {
          "_type_": "pipelinestage",
          "_children_": [
            {
              "_type_": "stage_id",
              "_value_": "2"
            },
            {
              "_type_": "stage_prerequisite",
              "_value_": "1"
            },
            {
              "_type_": "stage_isoutput",
              "_value_": "false"
            },
            {
              "_type_": "stage_connectionname",
              "_value_": "HTMLConnector"
            },
            {
              "_type_": "stage_specification",
              "_children_": [
                {
                  "_type_": "includefilter",
                  "_value_": "",
                  "_attribute_regex": "body"
                },
                {
                  "_type_": "excludefilter",
                  "_value_": "",
                  "_attribute_regex": "script"
                },
                {
                  "_type_": "striphtml",
                  "_value_": "",
                  "_attribute_value": "true"
                }
              ]
            }
          ]
        },
        {
          "_type_": "pipelinestage",
          "_children_": [
            {
              "_type_": "stage_id",
              "_value_": "3"
            },
            {
              "_type_": "stage_prerequisite",
              "_value_": "2"
            },
            {
              "_type_": "stage_isoutput",
              "_value_": "false"
            },
            {
              "_type_": "stage_connectionname",
              "_value_": "MetadataAdjuster"
            },
            {
              "_type_": "stage_specification",
              "_children_": [
                {
                  "_type_": "expression",
                  "_attribute_parameter": "repo_source",
                  "_value_": "",
                  "_attribute_value": "francelabs"
                },
                {
                  "_type_": "keepAllMetadata",
                  "_value_": "",
                  "_attribute_value": "true"
                },
                {
                  "_type_": "filterEmpty",
                  "_value_": "",
                  "_attribute_value": "false"
                }
              ]
            }
          ]
        },
        {
          "_type_": "pipelinestage",
          "_children_": [
            {
              "_type_": "stage_id",
              "_value_": "4"
            },
            {
              "_type_": "stage_prerequisite",
              "_value_": "3"
            },
            {
              "_type_": "stage_isoutput",
              "_value_": "false"
            },
            {
              "_type_": "stage_connectionname",
              "_value_": "TikaServerRmetaConnector"
            },
            {
              "_type_": "stage_specification",
              "_children_": [
                {
                  "_type_": "fieldmap",
                  "_attribute_target": "author",
                  "_value_": "",
                  "_attribute_source": "dc_creator"
                },
                {
                  "_type_": "fieldmap",
                  "_attribute_target": "last_author",
                  "_value_": "",
                  "_attribute_source": "meta_last_author"
                },
                {
                  "_type_": "fieldmap",
                  "_attribute_target": "title",
                  "_value_": "",
                  "_attribute_source": "dc_title"
                },
                {
                  "_type_": "fieldmap",
                  "_attribute_target": "creation_date",
                  "_value_": "",
                  "_attribute_source": "dcterms_created"
                },
                {
                  "_type_": "fieldmap",
                  "_attribute_target": "last_modified",
                  "_value_": "",
                  "_attribute_source": "dcterms_modified"
                },
                {
                  "_type_": "fieldmap",
                  "_attribute_target": "character_count",
                  "_value_": "",
                  "_attribute_source": "meta_character_count"
                },
                {
                  "_type_": "fieldmap",
                  "_attribute_target": "keywords",
                  "_value_": "",
                  "_attribute_source": "meta_keyword"
                },
                {
                  "_type_": "fieldmap",
                  "_attribute_target": "subject",
                  "_value_": "",
                  "_attribute_source": "dc_subject"
                },
                {
                  "_type_": "fieldmap",
                  "_attribute_target": "page_count",
                  "_value_": "",
                  "_attribute_source": "meta_page_count"
                },
                {
                  "_type_": "fieldmap",
                  "_attribute_target": "revision_number",
                  "_value_": "",
                  "_attribute_source": "cp_revision"
                },
                {
                  "_type_": "fieldmap",
                  "_attribute_target": "word_count",
                  "_value_": "",
                  "_attribute_source": "meta_word_count"
                },
                {
                  "_type_": "fieldmap",
                  "_attribute_target": "publisher",
                  "_value_": "",
                  "_attribute_source": "dc_publisher"
                },
                {
                  "_type_": "fieldmap",
                  "_attribute_target": "description",
                  "_value_": "",
                  "_attribute_source": "dc_description"
                },
                {
                  "_type_": "fieldmap",
                  "_attribute_target": "total_time",
                  "_value_": "",
                  "_attribute_source": "extended_properties_totaltime"
                },
                {
                  "_type_": "keepAllMetadata",
                  "_value_": "",
                  "_attribute_value": "true"
                },
                {
                  "_type_": "lowerNames",
                  "_value_": "",
                  "_attribute_value": "true"
                },
                {
                  "_type_": "writeLimit",
                  "_value_": "",
                  "_attribute_value": "1000000"
                },
                {
                  "_type_": "maxMetadataValueLength",
                  "_value_": "",
                  "_attribute_value": "250000"
                },
                {
                  "_type_": "totalMetadataLimit",
                  "_value_": "",
                  "_attribute_value": "500000"
                },
                {
                  "_type_": "extractArchives",
                  "_value_": "",
                  "_attribute_value": "false"
                }
              ]
            }
          ]
        },
        {
          "_type_": "pipelinestage",
          "_children_": [
            {
              "_type_": "stage_id",
              "_value_": "5"
            },
            {
              "_type_": "stage_prerequisite",
              "_value_": "4"
            },
            {
              "_type_": "stage_isoutput",
              "_value_": "false"
            },
            {
              "_type_": "stage_connectionname",
              "_value_": "MetadataCleaner"
            },
            {
              "_type_": "stage_specification",
              "_children_": [
                {
                  "_type_": "namecleaner",
                  "_value_": "",
                  "_attribute_value": "_{",
                  "_attribute_regex": "\\$\\{"
                },
                {
                  "_type_": "valuecleaner",
                  "_value_": "",
                  "_attribute_value": "_{",
                  "_attribute_regex": "\\$\\{"
                }
              ]
            }
          ]
        },
        {
          "_type_": "pipelinestage",
          "_children_": [
            {
              "_type_": "stage_id",
              "_value_": "6"
            },
            {
              "_type_": "stage_prerequisite",
              "_value_": "5"
            },
            {
              "_type_": "stage_isoutput",
              "_value_": "true"
            },
            {
              "_type_": "stage_connectionname",
              "_value_": "DatafariSolrNoTika"
            },
            {
              "_type_": "stage_specification"
            }
          ]
        },
        {
          "_type_": "start_mode",
          "_value_": "schedule window start"
        },
        {
          "_type_": "run_mode",
          "_value_": "scan once"
        },
        {
          "_type_": "hopcount_mode",
          "_value_": "accurate"
        },
        {
          "_type_": "priority",
          "_value_": "5"
        },
        {
          "_type_": "recrawl_interval",
          "_value_": "86400000"
        },
        {
          "_type_": "max_recrawl_interval",
          "_value_": "infinite"
        },
        {
          "_type_": "expiration_interval",
          "_value_": "infinite"
        },
        {
          "_type_": "reseed_interval",
          "_value_": "3600000"
        },
        {
          "_type_": "hopcount",
          "_children_": [
            {
              "_type_": "link_type",
              "_value_": "link"
            },
            {
              "_type_": "count",
              "_value_": "4"
            }
          ]
        }
      ]
    }
  ]
}